micropython_icm20948/__init__.py
micropython_icm20948/i2c_helpers.py
micropython_icm20948/icm20948.py
micropython_icm20948-0.2.3.dist-info/LICENSE
micropython_icm20948-0.2.3.dist-info/METADATA
micropython_icm20948-0.2.3.dist-info/WHEEL
micropython_icm20948-0.2.3.dist-info/top_level.txt
micropython_icm20948-0.2.3.dist-info/RECORD
