Metadata-Version: 2.1
Name: micropython-icm20948
Version: 0.2.3
Summary: MicroPython Driver for the Accelerometer and Gyro ICM20948 Sensor
Author-email: "Jose D. Montoya" <icm20948@mailmeto.mozmail.com>
License: MIT
Project-URL: Homepage, https://github.com/jposada202020/MicroPython_ICM20948
Keywords: micropython,icm20948,gyro,accelerometer,acceleration,sensor,tdk
Classifier: Intended Audience :: Developers
Classifier: Topic :: Software Development :: Libraries
Classifier: Topic :: Software Development :: Embedded Systems
Classifier: Topic :: System :: Hardware
Classifier: License :: OSI Approved :: MIT License
Classifier: Programming Language :: Python :: Implementation :: MicroPython
License-File: LICENSE
